[
  {
    "id": 1,
    "nombre": "Maria Soledad",
    "area": "Inventario",
    "contraseña": "12345",
    "rol": "usuario"
  },
  {
    "id": 2,
    "nombre": "Pepito Garcia",
    "area": "Ventas",
    "contraseña": "123",
    "rol": "admin"
  },
  {
    "id": 3,
    "nombre": "Lita Delazari",
    "area": "Ventas",
    "contraseña": "1414",
    "rol": "usuario"
  },
  {
    "id": 4,
    "nombre": "Carlos Mendoza",
    "area": "Recursos Humanos",
    "contraseña": "123",
    "rol": "admin"
  },
  {
    "id": 5,
    "nombre": "Ana Torres",
    "area": "Marketing",
    "contraseña": "12345",
    "rol": "usuario"
  },
  {
    "id": 7,
    "nombre": "Laura Sánchez",
    "area": "Finanzas",
    "contraseña": "12345",
    "rol": "admin"
  },
  {
    "id": 8,
    "nombre": "Fernando Ruiz",
    "area": "Soporte Técnico",
    "contraseña": "123456",
    "rol": "usuario"
  },
  {
    "id": 9,
    "nombre": "Lucia Jimenez",
    "area": "IT",
    "contraseña": "12345",
    "rol": "usuario"
  },
  {
    "id": 10,
    "nombre": "Gabriel Ortega",
    "area": "Desarrollo",
    "contraseña": "devpass",
    "rol": "admin"
  },
  {
    "id": 11,
    "nombre": "Ricardo González",
    "area": "Ventas",
    "contraseña": "1234",
    "rol": "usuario"
  },
  {
    "id": 12,
    "nombre": "Pablo Medina",
    "area": "Compras",
    "contraseña": "1234",
    "rol": "usuario"
  },
  {
    "id": 13,
    "nombre": "Isabella López",
    "area": "Marketing",
    "contraseña": "123",
    "rol": "admin"
  },
  {
    "id": 14,
    "nombre": "María Valenzuela",
    "area": "Ventas",
    "contraseña": "12345",
    "rol": "usuario"
  },
  {
    "id": 15,
    "nombre": "Graciela Patricia",
    "area": "Ventas",
    "contraseña": "12345"
  }
]